platformer_world/__init__.py
platformer_world/enemies.py
platformer_world/groups.py
platformer_world/level.py
platformer_world/main.py
platformer_world/player.py
platformer_world/settings.py
platformer_world/sprites.py
platformer_world/support.py
platformer_world/timer.py
platformer_world/audio/attack.wav
platformer_world/audio/coin.wav
platformer_world/audio/damage.wav
platformer_world/audio/hit.wav
platformer_world/audio/jump.wav
platformer_world/audio/pearl.wav
platformer_world/audio/starlight_city.mp3
platformer_world/data/levels/0.tmx
platformer_world/data/levels/1.tmx
platformer_world/data/levels/2.tmx
platformer_world/data/levels/3.tmx
platformer_world/data/levels/4.tmx
platformer_world/data/levels/5.tmx
platformer_world/data/levels/6.tmx
platformer_world/data/levels/omni.tmx
platformer_world/data/overworld/overworld.tmx
platformer_world/data/tilesets/editor_paths.tsx
platformer_world/data/tilesets/enemies.tsx
platformer_world/data/tilesets/extra.tsx
platformer_world/data/tilesets/grass.tsx
platformer_world/data/tilesets/inside.tsx
platformer_world/data/tilesets/items.tsx
platformer_world/data/tilesets/map objects.tsx
platformer_world/data/tilesets/objects.tsx
platformer_world/data/tilesets/outside.tsx
platformer_world/data/tilesets/overworld.tsx
platformer_world/data/tilesets/platforms.tsx
platformer_world/graphics/effects/particle/0.png
platformer_world/graphics/effects/particle/1.png
platformer_world/graphics/effects/particle/2.png
platformer_world/graphics/enemies/bullets/pearl.png
platformer_world/graphics/enemies/floor_spikes/0.png
platformer_world/graphics/enemies/floor_spikes/1.png
platformer_world/graphics/enemies/floor_spikes/2.png
platformer_world/graphics/enemies/floor_spikes/3.png
platformer_world/graphics/enemies/saw/saw_chain.png
platformer_world/graphics/enemies/saw/animation/0.png
platformer_world/graphics/enemies/saw/animation/1.png
platformer_world/graphics/enemies/saw/animation/2.png
platformer_world/graphics/enemies/saw/animation/3.png
platformer_world-0.0.7.dist-info/METADATA
platformer_world-0.0.7.dist-info/WHEEL
platformer_world-0.0.7.dist-info/entry_points.txt
platformer_world-0.0.7.dist-info/RECORD
