Metadata-Version: 2.4
Name: platformer-world
Version: 0.0.7
Summary: 2D Platformer written in pygame
Project-URL: Repository, https://github.com/Dekoder-py/PygamePlatformer
Author-email: Dekoder-py <dekod3r.py@gmail.com>
License-Expression: MIT
Keywords: adventure,game,interactive,platformer,pygame
Requires-Python: >=3.7
Requires-Dist: pygame-ce
Requires-Dist: pytmx
